{
  "fluentMethods": true,
  "relationships": [
      {
          "relationshipType": "one-to-one",
          "relationshipName": "user",
          "otherEntityName": "user",
          "otherEntityField": "id",
          "ownerSide": true,
          "otherEntityRelationshipName": "userExtended"
      }
  ],
  "fields": [
      {
          "fieldName": "phone",
          "fieldType": "String"
      }
  ],
  "changelogDate": "20220713102526",
  "dto": "no",
  "service": "no",
  "entityTableName": "user_extended",
  "jpaMetamodelFiltering": false,
  "pagination": "no"
}